pydoodle/__init__.py
pydoodle/errors.py
pydoodle/jdoodle.py
pydoodle-1.1.3.dist-info/LICENSE
pydoodle-1.1.3.dist-info/METADATA
pydoodle-1.1.3.dist-info/WHEEL
pydoodle-1.1.3.dist-info/top_level.txt
pydoodle-1.1.3.dist-info/RECORD
