Metadata-Version: 2.1
Name: pydoodle
Version: 1.1.3
Summary: An API wrapper of Jdoodle.com
Home-page: https://github.com/Prince2347X/pydoodle
Author: Prince2347X
Author-email: prince.raj29042004@gmail.com
License: MIT
Project-URL: Source Code, https://github.com/Prince2347X/pydoodle
Project-URL: Issue Tracker, https://github.com/Prince2347X/pydoodle/issues
Project-URL: Documentation, https://pydoodle.readthedocs.io/
Keywords: compiler,compiler api,jdoodle,jdoodle api,pydoodle,jdoodle python
Platform: UNKNOWN
Classifier: Intended Audience :: Developers
Classifier: Intended Audience :: Information Technology
Classifier: Operating System :: OS Independent
Classifier: Topic :: Software Development :: Compilers
Classifier: Topic :: Documentation :: Sphinx
Classifier: License :: OSI Approved :: MIT License
Classifier: Programming Language :: Python :: 3.5
Classifier: Programming Language :: Python :: 3.6
Classifier: Programming Language :: Python :: 3.7
Classifier: Programming Language :: Python :: 3.8
Classifier: Programming Language :: Python :: 3.9
Classifier: Programming Language :: Python :: 3.10
Classifier: Natural Language :: English
Requires-Python: >=3.5.1
Requires-Dist: requests (==2.25.1)
